anansi_market_data_handler/__init__.py
anansi_market_data_handler/brokers.py
anansi_market_data_handler/db_handlers.py
anansi_market_data_handler/indicators.py
anansi_market_data_handler/klines.py
anansi_market_data_handler/my_tools.py
anansi_market_data_handler/settings.py
anansi_market_data_handler-0.2.1.dist-info/WHEEL
anansi_market_data_handler-0.2.1.dist-info/METADATA
anansi_market_data_handler-0.2.1.dist-info/RECORD
